fast_temporal/__init__.py
fast_temporal/api/__init__.py
fast_temporal/api/fastapi.py
fast_temporal/config/__init__.py
fast_temporal/config/config.py
fast_temporal/workflow/__init__.py
fast_temporal/workflow/workflow.py
fast_temporal-0.3.dist-info/METADATA
fast_temporal-0.3.dist-info/WHEEL
fast_temporal-0.3.dist-info/entry_points.txt
fast_temporal-0.3.dist-info/top_level.txt
fast_temporal-0.3.dist-info/RECORD
