Metadata-Version: 2.4
Name: fast_temporal
Version: 0.3
Summary: A FastAPI app that communicates with a generic Temporal and streams updates via websocket.
Author-email: Vinnakota Harshith <v.harshith2000@gmail.com>
Project-URL: Homepage, https://github.com/harshith242/fast_temporal
Classifier: Programming Language :: Python :: 3
Classifier: Framework :: FastAPI
Classifier: Topic :: Software Development :: Libraries
Classifier: Intended Audience :: Developers
Classifier: Operating System :: OS Independent
Requires-Python: >=3.8
Requires-Dist: fastapi
Requires-Dist: uvicorn[standard]
Requires-Dist: python-dotenv
Requires-Dist: temporalio
Requires-Dist: websockets
